sentry_auth_ldap/backend.py
sentry_auth_ldap-24.8.1.post1.dist-info/licenses/LICENSE.txt
sentry_auth_ldap-24.8.1.post1.dist-info/METADATA
sentry_auth_ldap-24.8.1.post1.dist-info/WHEEL
sentry_auth_ldap-24.8.1.post1.dist-info/top_level.txt
sentry_auth_ldap-24.8.1.post1.dist-info/RECORD
