Metadata-Version: 2.4
Name: sentry-auth-ldap
Version: 24.8.1.post1
Summary: A Sentry extension to add an LDAP server as an authentication source.
Home-page: https://github.com/PMExtra/sentry-auth-ldap
Download-URL: https://github.com/PMExtra/sentry-auth-ldap
Author: Chad Killingsworth <chad.killingsworth@banno.com>, Barron Hagerman <barron.hagerman@banno.com>, PM Extra <pm@jubeat.net>
Author-email: pm@jubeat.net
License: Apache-2.0
Project-URL: Bug Tracker, https://github.com/PMExtra/sentry-auth-ldap/issues
Project-URL: CI, https://github.com/PMExtra/sentry-auth-ldap/actions
Project-URL: Source Code, https://github.com/PMExtra/sentry-auth-ldap
Classifier: Framework :: Django
Classifier: Intended Audience :: Developers
Classifier: Intended Audience :: System Administrators
Classifier: Operating System :: OS Independent
Classifier: Programming Language :: Python :: 3
Classifier: Topic :: Software Development
License-File: LICENSE.txt
Requires-Dist: django-auth-ldap==4.1.0
Requires-Dist: sentry>=23.6.0
Dynamic: author
Dynamic: author-email
Dynamic: classifier
Dynamic: description
Dynamic: description-content-type
Dynamic: download-url
Dynamic: home-page
Dynamic: license
Dynamic: license-file
Dynamic: project-url
Dynamic: requires-dist
Dynamic: summary
